neon_cli/__init__.py
neon_cli/__main__.py
neon_cli/cli.py
neon_cli/gui_server.py
neon_cli/text_client.py
neon_cli/utils.py
neon_cli_client-0.3.1.dist-info/LICENSE.md
neon_cli_client-0.3.1.dist-info/METADATA
neon_cli_client-0.3.1.dist-info/WHEEL
neon_cli_client-0.3.1.dist-info/entry_points.txt
neon_cli_client-0.3.1.dist-info/top_level.txt
neon_cli_client-0.3.1.dist-info/RECORD
