Metadata-Version: 2.1
Name: neon-cli-client
Version: 0.3.1
Summary: Packaged CLI Client from Neon, Mycroft, and OVOS cores
Home-page: https://github.com/NeonGeckoCom/neon_cli
Author: Neongecko
Author-email: developers@neon.ai
License: apache-2.0
License-File: LICENSE.md
Requires-Dist: ovos-bus-client~=0.0
Requires-Dist: neon-utils~=1.0
Requires-Dist: ovos-config~=0.0
Requires-Dist: click~=8.0
Requires-Dist: click-default-group~=1.2
